MANIFEST.in
setup.py
src/masonite/testing/drivers/chrome/ChromeDriver.py
src/masonite/testing/drivers/chrome/linux/chromedriver74
src/masonite/testing/drivers/chrome/linux/chromedriver75
src/masonite/testing/drivers/chrome/linux/chromedriver76
src/masonite/testing/drivers/chrome/mac/chromedriver74
src/masonite/testing/drivers/chrome/mac/chromedriver75
src/masonite/testing/drivers/chrome/mac/chromedriver76
src/masonite/testing/drivers/chrome/windows/chromedriver74.exe
src/masonite/testing/drivers/chrome/windows/chromedriver75.exe
src/masonite/testing/drivers/chrome/windows/chromedriver76.exe
src/masonite/testing/drivers/firefox/FirefoxDriver.py
src/masonite/testing/drivers/firefox/linux/geckodriver-32
src/masonite/testing/drivers/firefox/linux/geckodriver-64
src/masonite/testing/drivers/firefox/mac/geckodriver
src/masonite/testing/drivers/firefox/windows/geckodriver-32.exe
src/masonite/testing/drivers/firefox/windows/geckodriver-64.exe
src/masonite/testing/selenium/SeleniumTestCase.py
src/masonite/testing/selenium/__init__.py
src/masonite_selenium.egg-info/PKG-INFO
src/masonite_selenium.egg-info/SOURCES.txt
src/masonite_selenium.egg-info/dependency_links.txt
src/masonite_selenium.egg-info/requires.txt
src/masonite_selenium.egg-info/top_level.txt